zalgo_cli/__init__.py
zalgo_cli/app.py
zalgo_cli/cli.py
zalgo_cli/requirements.txt
zalgo_cli-0.5.0.dist-info/LICENSE
zalgo_cli-0.5.0.dist-info/METADATA
zalgo_cli-0.5.0.dist-info/WHEEL
zalgo_cli-0.5.0.dist-info/entry_points.txt
zalgo_cli-0.5.0.dist-info/RECORD
