Metadata-Version: 2.1
Name: zalgo-cli
Version: 0.5.0
Summary: Zalgo Text Generator CLI
Home-page: https://github.com/tddschn/zalgo-cli
License: MIT
Keywords: zalgo
Author: Teddy Xinyuan Chen
Author-email: 45612704+tddschn@users.noreply.github.com
Requires-Python: >=3.10,<4.0
Classifier: License :: OSI Approved :: MIT License
Classifier: Programming Language :: Python :: 3
Classifier: Programming Language :: Python :: 3.10
Classifier: Programming Language :: Python :: 3.11
Classifier: Programming Language :: Python :: 3.12
Classifier: Topic :: Utilities
Requires-Dist: gradio[gradio] (>=4.36.1,<5.0.0)
Project-URL: Bug Tracker, https://github.com/tddschn/zalgo-cli/issues
Project-URL: Repository, https://github.com/tddschn/zalgo-cli
